mgpy/mgnum.py
mgpy/mgstr.py
mgpy-0.1.3.dist-info/METADATA
mgpy-0.1.3.dist-info/WHEEL
mgpy-0.1.3.dist-info/licenses/LICENSE
mgpy-0.1.3.dist-info/RECORD
