Metadata-Version: 2.3
Name: mgpy
Version: 0.1.3
Summary: A small package containing simple, useful methods I regularly use and don't want to manually copy into several projects. Most methods are probably to be found in other modules.
Project-URL: Homepage, https://github.com/phistoh/mgpy
Author-email: Moritz <phis@mogobb.de>
Classifier: Development Status :: 1 - Planning
Classifier: License :: OSI Approved :: MIT License
Classifier: Operating System :: OS Independent
Classifier: Programming Language :: Python :: 3.11
Classifier: Topic :: Software Development :: Libraries
Requires-Python: >=3.11
